[{"url":"/front-end/vue/keep-alive-bug","categories":["front-end","vue"],"category":"vue","created":"2024-09-27","title":"vue3 KeepAlive 组件缓存失效 bug 分析 <Badge type=\"danger\" text=\"BUG\" />"},{"url":"/front-end/engineering/filter-rollup-warn","categories":["front-end","engineering"],"category":"engineering","created":"2024-9-25","title":"Rollup Annotation 警告处理"},{"url":"/front-end/vue/open-route-on-new-tab","categories":["front-end","vue"],"category":"vue","created":"2024-09-14","title":"vue-router 在新的标签页打开链接/路由"},{"url":"/study/note/review-array","categories":["study","note"],"category":"note","created":"2024-09-04","title":"Array 查缺补漏"},{"url":"/front-end/others/xlsx-export-excel","categories":["front-end","others"],"category":"others","created":"2024-08-15","title":"xlsx导出excel功能封装"},{"url":"/front-end/basic/js/xmlserializer-style-bug","categories":["front-end","basic"],"category":"basic","created":"2024-07-29","title":"XMLSerializer序列化style元素时存在转译bug <Badge type=\"danger\" text=\"BUG\" />"},{"url":"/front-end/engineering/uglifyjs-echarts-bug","categories":["front-end","engineering"],"category":"engineering","created":"2024-07-25","title":"uglifyjs压缩代码导致echarts图表UI异常 <Badge type=\"danger\" text=\"BUG\" />"},{"url":"/front-end/basic/others/axios-progressevent-total","categories":["front-end","basic"],"category":"basic","created":"2024-07-23","title":"axios下载进度api无法获取响应大小 <Badge type=\"danger\" text=\"BUG\" />"},{"url":"/front-end/engineering/manage-node","categories":["front-end","engineering"],"category":"engineering","created":"2024-07-17","title":"node环境管理"},{"url":"/study/cheatsheets/typescript","categories":["study","cheatsheets"],"category":"cheatsheets","created":"2024-07-17","title":"typescript 速查表"},{"url":"/front-end/engineering/deploy","categories":["front-end","engineering"],"category":"engineering","created":"2024-07-12","title":"前端项目部署"},{"url":"/study/read/set-methods","categories":["study","read"],"category":"read","created":"2024-07-01","title":"Set新方法学习"},{"url":"/study/source-code/mitt","categories":["study","source-code"],"category":"source-code","created":"2024-06-28","title":"Mitt源码学习"},{"url":"/front-end/engineering/github-actions","categories":["front-end","engineering"],"category":"engineering","created":"2024-06-27","title":"Github Actions 使用记录"},{"url":"/front-end/others/vitepress-usage","categories":["front-end","others"],"category":"others","created":"2024-06-27","title":"vitepress静态站点生成"},{"url":"/front-end/basic/js/base64-zh","categories":["front-end","basic"],"category":"basic","created":"2024-06-25","title":"中文字符串base64编码、解码"},{"url":"/front-end/basic/js/utils","categories":["front-end","basic"],"category":"basic","created":"2024-06-25","title":"实用 js 工具方法"},{"url":"/front-end/basic/js/image-base64-appl","categories":["front-end","basic"],"category":"basic","created":"2024-06-20","title":"图片base64编码、解码、下载"},{"url":"/front-end/vue/data-store","categories":["front-end","vue"],"category":"vue","created":"2024-06-20","title":"vue3 局部状态管理"},{"url":"/front-end/nodejs/mailer-service","categories":["front-end","nodejs"],"category":"nodejs","created":"2024-04-30","title":"基于 nodejs 的邮件服务"},{"url":"/front-end/others/syntactic-highlighting-and-marked","categories":["front-end","others"],"category":"others","created":"2024-04-30","title":"代码语法高亮 + markdown解析"},{"url":"/study/note/review-vue-component","categories":["study","note"],"category":"note","created":"2023-12-18","title":"vue3查缺补漏-组件"},{"url":"/study/note/review-vue-base","categories":["study","note"],"category":"note","created":"2023-11-29","title":"vue3查缺补漏-基础"},{"url":"/front-end/element-plus/prevload-dialog","categories":["front-end","element-plus"],"category":"element-plus","created":"2023-09-21","title":"预加载 Element Plus 的 Dialog 组件"},{"url":"/front-end/element-plus/auto-resizer","categories":["front-end","element-plus"],"category":"element-plus","created":"2023-09-13","title":"ElementPlus ElAutoResizer 组件的使用"},{"url":"/front-end/basic/js/js-doc","categories":["front-end","basic"],"category":"basic","created":"2023-09-12","title":"js 文档注释规范"},{"url":"/front-end/engineering/pack-svg","categories":["front-end","engineering"],"category":"engineering","created":"2023-09-12","title":"vue项目中封装使用svg组件"},{"url":"/front-end/engineering/uniform-code-style","categories":["front-end","engineering"],"category":"engineering","created":"2023-09-12","title":"实践：新手使用 ESLint 进行项目代码检测与格式化"},{"url":"/front-end/vue/vue-svg-comp","categories":["front-end","vue"],"category":"vue","created":"2023-09-12","title":"vue 项目中使用 svg 组件"},{"url":"/front-end/engineering/package-optimize","categories":["front-end","engineering"],"category":"engineering","created":"2023-07-03","title":"优化 Webpack 打包流程：打包完成后再删除旧文件，确保网站访问稳定"},{"url":"/front-end/basic/others/encapsulate-axios","categories":["front-end","basic"],"category":"basic","created":"2023-05-29","title":"axios 封装"},{"url":"/study/book/pro-js/chapter11-2","categories":["study","book"],"category":"book","created":"2023-04-18","title":"第11章 第2节 期约"},{"url":"/front-end/element-plus/tablev2","categories":["front-end","element-plus"],"category":"element-plus","created":"2023-03-13","title":"Element Plus 虚拟化表格组件的使用(排序、筛选、自定义单元格渲染) - 个人使用总结"},{"url":"/front-end/element-plus/tablev1-multi-select","categories":["front-end","element-plus"],"category":"element-plus","created":"2023-02-14","title":"实现 element-plus 表格多选时按 shift 进行连选的功能"},{"url":"/front-end/element-plus/tablev1-track-data","categories":["front-end","element-plus"],"category":"element-plus","created":"2023-01-19","title":"Element Plus 跟踪表格数据总数，包括查询、筛选等操作"},{"url":"/front-end/vue/vue3-grammar","categories":["front-end","vue"],"category":"vue","created":"2022-07-01","title":"上手 vue3 组合式API (Composition API) --- 语法要点总结"},{"url":"/front-end/vue/dark-mode","categories":["front-end","vue"],"category":"vue","created":"2022-06-29","title":"基于 vue3 & element-plus 的暗黑模式"},{"url":"/front-end/basic/js/regex","categories":["front-end","basic"],"category":"basic","created":"2022-06-09","title":"正则表达式使用"},{"url":"/study/book/pro-js/chapter7","categories":["study","book"],"category":"book","created":"2022-04-24","title":"第7章 迭代器与生成器"},{"url":"/study/book/pro-js/chapter8","categories":["study","book"],"category":"book","created":"2022-04-24","title":"第8章 对象、类与面向对象编程"},{"url":"/front-end/basic/css/style-adaptation","categories":["front-end","basic"],"category":"basic","created":"2022-04-14","title":"CSS移动端适配"},{"url":"/front-end/basic/js/performance-optimization-of-image","categories":["front-end","basic"],"category":"basic","created":"2022-04-14","title":"网页性能优化——图片，使用多种图片处理策略提升性能，包括压缩、云存储、预加载、懒加载、渐进式图片"},{"url":"/front-end/basic/js/encapsulate-async","categories":["front-end","basic"],"category":"basic","created":"2022-03-04","title":"async...await...异常捕捉封装"},{"url":"/front-end/vue/switch-within-route","categories":["front-end","vue"],"category":"vue","created":"2022-02-28","title":"vue相同的组件实例间跳转页面不刷新的问题分析"},{"url":"/front-end/element-plus/form-validate","categories":["front-end","element-plus"],"category":"element-plus","created":"2021-10-18","title":"element-plus 表单验证使用 个人总结"},{"url":"/front-end/vue/watch-keyup-event","categories":["front-end","vue"],"category":"vue","created":"2021-09-06","title":"vue组件中监听键盘/按键事件"},{"url":"/front-end/basic/css/css-media","categories":["front-end","basic"],"category":"basic","created":"2021-05-14","title":"css媒体查询总结"},{"url":"/back-end/mybatis-plus/custom-paged-query-join-sql","categories":["back-end","mybatis-plus"],"category":"mybatis-plus","created":"2021-01-13","title":"实例：MyBatis-Plus 自定义联表分页查询-动态 sql 实现"},{"url":"/front-end/basic/others/git-basic-usage","categories":["front-end","basic"],"category":"basic","created":"2020-11-18","title":"Git基本使用"},{"url":"/back-end/mybatis-plus/nested-query","categories":["back-end","mybatis-plus"],"category":"mybatis-plus","created":"2020-08-19","title":"Mybatis-Plus条件构造器and or嵌套使用"},{"url":"/back-end/mybatis-plus/custom-paged-query-join","categories":["back-end","mybatis-plus"],"category":"mybatis-plus","created":"2020-08-08","title":"实例：MyBatis-Plus 自定义联表分页查询"},{"url":"/back-end/mybatis-plus/custom-paged-query","categories":["back-end","mybatis-plus"],"category":"mybatis-plus","created":"2020-07-08","title":"实例：MyBatis-Plus自定义分页查询"},{"url":"/back-end/mybatis-plus/list-and-json-typehandler","categories":["back-end","mybatis-plus"],"category":"mybatis-plus","created":"2020-06-08","title":"PgSQL数组及json类型在Mybatis项目中的类型转换"},{"url":"/front-end/basic/js/load-and-export-excel","categories":["front-end","basic"],"category":"basic","created":"2020-03-07","title":"导入Excel数据以及导出表格数据成Excel"},{"url":"/front-end/element-plus/editable-table","categories":["front-end","element-plus"],"category":"element-plus","created":"2020-03-07","title":"vue3 + Element Plus动态生成表格，并实现内容可编辑"},{"url":"/back-end/python/friends-recommend","categories":["back-end","python"],"category":"python","created":"2020-01-02","title":"python实现用户好友推荐"},{"url":"/back-end/python/topic-recommend","categories":["back-end","python"],"category":"python","created":"2020-01-02","title":"python 基于 item-item filtering 实现话题推荐"}]